{
  "project_info": {
    "project_number": "575355286930",
    "firebase_url": "https://chatapp-c2de6-default-rtdb.europe-west1.firebasedatabase.app",
    "project_id": "chatapp-c2de6",
    "storage_bucket": "chatapp-c2de6.appspot.com"
  },
  "client": [
    {
      "client_info": {
        "mobilesdk_app_id": "1:575355286930:android:23eda6ecc0996013af7d4b",
        "android_client_info": {
          "package_name": "com.example.chat"
        }
      },
      "oauth_client": [],
      "api_key": [
        {
          "current_key": "AIzaSyB7uSdBfOdczocyzWS_WGL8Xp6PeSqKwsc"
        }
      ],
      "services": {
        "appinvite_service": {
          "other_platform_oauth_client": []
        }
      }
    },
    {
      "client_info": {
        "mobilesdk_app_id": "1:575355286930:android:fd713812350e964aaf7d4b",
        "android_client_info": {
          "package_name": "com.example.chats_app"
        }
      },
      "oauth_client": [],
      "api_key": [
        {
          "current_key": "AIzaSyB7uSdBfOdczocyzWS_WGL8Xp6PeSqKwsc"
        }
      ],
      "services": {
        "appinvite_service": {
          "other_platform_oauth_client": []
        }
      }
    },
    {
      "client_info": {
        "mobilesdk_app_id": "1:575355286930:android:afd769da9b29dc4aaf7d4b",
        "android_client_info": {
          "package_name": "dev.shoxrux_tm.chat_app"
        }
      },
      "oauth_client": [],
      "api_key": [
        {
          "current_key": "AIzaSyB7uSdBfOdczocyzWS_WGL8Xp6PeSqKwsc"
        }
      ],
      "services": {
        "appinvite_service": {
          "other_platform_oauth_client": []
        }
      }
    }
  ],
  "configuration_version": "1"
}